papyri/.DS_Store
papyri/__init__.py
papyri/__main__.py
papyri/browser.py
papyri/common_ast.py
papyri/config.py
papyri/core.py
papyri/crosslink.py
papyri/directives.py
papyri/errors.py
papyri/examples.py
papyri/gen.py
papyri/graphstore.py
papyri/ipython.py
papyri/jlab.py
papyri/miniserde.py
papyri/miscs.py
papyri/myst_ast.py
papyri/myst_serialiser.py
papyri/node_utils.py
papyri/py.types
papyri/render.py
papyri/rich_render.py
papyri/rst.so
papyri/signature.py
papyri/take2.py
papyri/textual.py
papyri/toc.py
papyri/tree.py
papyri/ts.py
papyri/utils.py
papyri/vref.py
papyri/app/asset-manifest.json
papyri/app/index.html
papyri/app/static/css/main.e6c13ad2.css
papyri/app/static/css/main.e6c13ad2.css.map
papyri/app/static/js/main.27408fde.js
papyri/app/static/js/main.27408fde.js.LICENSE.txt
papyri/app/static/js/main.27408fde.js.map
papyri/app/static/js/react-syntax-highlighter_languages_highlight_abnf.05a76338.chunk.js
papyri/app/static/js/react-syntax-highlighter_languages_highlight_abnf.05a76338.chunk.js.map
papyri/app/static/js/react-syntax-highlighter_languages_highlight_accesslog.32f749c7.chunk.js
papyri/app/static/js/react-syntax-highlighter_languages_highlight_accesslog.32f749c7.chunk.js.map
papyri/app/static/js/react-syntax-highlighter_languages_highlight_actionscript.bb38f24a.chunk.js
papyri/app/static/js/react-syntax-highlighter_languages_highlight_actionscript.bb38f24a.chunk.js.map
papyri/app/static/js/react-syntax-highlighter_languages_highlight_ada.481ce680.chunk.js
papyri/app/static/js/react-syntax-highlighter_languages_highlight_ada.481ce680.chunk.js.map
papyri/app/static/js/react-syntax-highlighter_languages_highlight_angelscript.98c5a3f3.chunk.js
papyri/app/static/js/react-syntax-highlighter_languages_highlight_angelscript.98c5a3f3.chunk.js.map
papyri/app/static/js/react-syntax-highlighter_languages_highlight_apache.2bda4313.chunk.js
papyri/app/static/js/react-syntax-highlighter_languages_highlight_apache.2bda4313.chunk.js.map
papyri-0.0.9.dist-info/entry_points.txt
papyri-0.0.9.dist-info/LICENSE
papyri-0.0.9.dist-info/WHEEL
papyri-0.0.9.dist-info/METADATA
papyri-0.0.9.dist-info/RECORD
