Metadata-Version: 2.1
Name: papyri
Version: 0.0.9
Summary: Papyri – in progress
Author-email: Matthias Bussonnier <bussonniermatthias@gmail.com>
Requires-Python: >=3.11
Classifier: License :: OSI Approved :: MIT License
Requires-Dist: black
Requires-Dist: flatlatex
Requires-Dist: httpx
Requires-Dist: ipython
Requires-Dist: jedi
Requires-Dist: jinja2>=3.1.2
Requires-Dist: numpydoc
Requires-Dist: pygments
Requires-Dist: quart-trio>=0.6.0
Requires-Dist: quart>=0.18.4
Requires-Dist: rich
Requires-Dist: tomli_w
Requires-Dist: typer>=0.9
Requires-Dist: urwid
Requires-Dist: velin
Requires-Dist: tree-sitter-builds
Requires-Dist: tree_sitter_languages>=1.5
Requires-Dist: matplotlib
Requires-Dist: cbor2
Requires-Dist: minify_html
Requires-Dist: textual
Requires-Dist: emoji
Project-URL: Home, https://github.com/Jupyter/papyri
